Metadata-Version: 2.1
Name: mf4readerpackage
Version: 1.0
Summary: A Measured Data Format file parser. Fork of mdfreader.
Home-page: https://github.com/ratal/mdfreader
Author: Venu Myneni
Author-email: mailvenumyneni@gmail.com
License: GPL3
Keywords: Parser MDF file
Platform: UNKNOWN
Classifier: Development Status :: 4 - Beta
Classifier: Intended Audience :: Science/Research
Classifier: Topic :: Scientific/Engineering
Classifier: License :: OSI Approved :: GNU General Public License v3 or later (GPLv3+)
Classifier: Programming Language :: Python :: 3.5
Classifier: Programming Language :: Python :: 3.6
Classifier: Programming Language :: Python :: 3.7
Classifier: Programming Language :: Python :: 3.8
License-File: LICENSE
License-File: COPYING
Requires-Dist: numpy (>=1.14)
Requires-Dist: sympy
Requires-Dist: lxml
Requires-Dist: bitarray
Provides-Extra: compression
Requires-Dist: blosc ; extra == 'compression'
Provides-Extra: converter
Requires-Dist: PyQt5 ; extra == 'converter'
Provides-Extra: export
Requires-Dist: hdf5storage ; extra == 'export'
Requires-Dist: h5py ; extra == 'export'
Requires-Dist: scipy ; extra == 'export'
Requires-Dist: xlwt ; extra == 'export'
Requires-Dist: xlwt3 ; extra == 'export'
Requires-Dist: openpyxl (>2.0) ; extra == 'export'
Requires-Dist: pandas ; extra == 'export'
Requires-Dist: fastparquet ; extra == 'export'
Provides-Extra: plot
Requires-Dist: matplotlib ; extra == 'plot'
Requires-Dist: mpldatacursor ; extra == 'plot'
